tado/__init__.py
tado/base.py
tado/enums.py
tado/offsets.py
tado/utils.py
tado/version.py
tado_overseer-0.0.3.dist-info/LICENSE
tado_overseer-0.0.3.dist-info/METADATA
tado_overseer-0.0.3.dist-info/WHEEL
tado_overseer-0.0.3.dist-info/top_level.txt
tado_overseer-0.0.3.dist-info/RECORD
